torchsummary/__init__.py
torchsummary/torchsummary.py
torchsummary-1.5.dist-info/METADATA
torchsummary-1.5.dist-info/RECORD
torchsummary-1.5.dist-info/WHEEL
torchsummary-1.5.dist-info/top_level.txt
