Metadata-Version: 2.1
Name: torchsummary
Version: 1.5
Summary: Model summary in PyTorch similar to `model.summary()` in Keras
Home-page: https://github.com/sksq96/pytorch-summary
Author: Shubham Chandel @sksq96
Author-email: shubham.zeez@gmail.com
License: UNKNOWN
Platform: UNKNOWN
